odoo/addons/ssi_work_log_cost/README.rst
odoo/addons/ssi_work_log_cost/__init__.py
odoo/addons/ssi_work_log_cost/__manifest__.py
odoo/addons/ssi_work_log_cost/data/approval_template_data.xml
odoo/addons/ssi_work_log_cost/data/ir_sequence_data.xml
odoo/addons/ssi_work_log_cost/data/policy_template_data.xml
odoo/addons/ssi_work_log_cost/data/sequence_template_data.xml
odoo/addons/ssi_work_log_cost/models/__init__.py
odoo/addons/ssi_work_log_cost/models/hr_employee.py
odoo/addons/ssi_work_log_cost/models/hr_work_log.py
odoo/addons/ssi_work_log_cost/models/ir_model.py
odoo/addons/ssi_work_log_cost/models/work_log_rate.py
odoo/addons/ssi_work_log_cost/models/work_log_rate_general_rate.py
odoo/addons/ssi_work_log_cost/security/ir.model.access.csv
odoo/addons/ssi_work_log_cost/security/ir_module_category_data.xml
odoo/addons/ssi_work_log_cost/security/ir_rule_data.xml
odoo/addons/ssi_work_log_cost/security/res_group_data.xml
odoo/addons/ssi_work_log_cost/static/description/icon.png
odoo/addons/ssi_work_log_cost/views/hr_employee_views.xml
odoo/addons/ssi_work_log_cost/views/hr_work_log_views.xml
odoo/addons/ssi_work_log_cost/views/ir_model_views.xml
odoo/addons/ssi_work_log_cost/views/work_log_rate_views.xml
odoo14_addon_ssi_work_log_cost-14.0.1.6.0.dist-info/METADATA
odoo14_addon_ssi_work_log_cost-14.0.1.6.0.dist-info/WHEEL
odoo14_addon_ssi_work_log_cost-14.0.1.6.0.dist-info/top_level.txt
odoo14_addon_ssi_work_log_cost-14.0.1.6.0.dist-info/RECORD
